Workbook

Sheet Registro de Gastos
A1: CONTROL DE GASTOS - FINCA AGROPECUARIA
A2: Registra tus gastos diarios — Claude los categoriza automáticamente
A3: Fecha | B3: Descripción del Gasto | C3: Categoría | D3: Subcategoría | E3: Proveedor | F3: Cantidad | G3: Unidad | H3: Valor Unit. ($) | I3: Total ($) | J3: Notas
A4: 2025-04-27 | B4: Vacuna aftosa x20 dosis | C4: Sanidad animal | D4: Vacunas | E4: Distribuidora Agro Ltda | F4: 20 | G4: dosis | H4: 2250 | I4: =F4*H4 | J4: Lote 12 - terneros
A5: 2025-04-27 | B5: Sal mineralizada 2 bultos | C5: Alimentación animal | D5: Minerales | E5: Almacén El Campo | F5: 2 | G5: bultos | H5: 80000 | I5: =F5*H5
A6: 2025-04-27 | B6: Jornal - Pedro Martínez | C6: Mano de obra | D6: Jornales | E6: Pedro Martínez | F6: 1 | G6: jornal | H6: 50000 | I6: =F6*H6 | J6: Chapeo potrero 3
A7: 2025-04-27 | B7: Gasolina motosierra | C7: Maquinaria y equipos | D7: Combustible | E7: Estación Mobil | F7: 5 | G7: litros | H7: 5000 | I7: =F7*H7
A8: 2025-04-28 | B8: Concentrado bovino 3 bultos | C8: Alimentación animal | D8: Concentrados | E8: Contegral | F8: 3 | G8: bultos | H8: 95000 | I8: =F8*H8 | J8: Para terneras en cría
A9: 2025-04-28 | B9: Ivermectina 500ml | C9: Sanidad animal | D9: Antiparasitarios | E9: Vetamar | F9: 1 | G9: frasco | H9: 45000 | I9: =F9*H9 | J9: Desparasitación mensual
A10: 2025-04-28 | B10: Alambre de púas rollo | C10: Insumos agrícolas | D10: Cercas | E10: Ferretería Central | F10: 2 | G10: rollos | H10: 78000 | I10: =F10*H10 | J10: Reparación cercado norte
A11: 2025-04-29 | B11: Herbicida glifosato 1L | C11: Insumos agrícolas | D11: Agroquímicos | E11: Agroservicios | F11: 4 | G11: litros | H11: 22000 | I11: =F11*H11 | J11: Control malezas potrero 1
A12: 2025-04-29 | B12: Almuerzo trabajadores | C12: Mano de obra | D12: Alimentación personal | E12: Comedor El Campesino | F12: 3 | G12: almuerzos | H12: 12000 | I12: =F12*H12
A13: 2025-04-30 | B13: Flete transporte ganado | C13: Transporte | D13: Flete ganado | E13: Transportes Boyacá | F13: 1 | G13: viaje | H13: 180000 | I13: =F13*H13 | J13: Subasta Sogamoso
I14: =IF(F14="","",F14*H14)
I15: =IF(F15="","",F15*H15)
I16: =IF(F16="","",F16*H16)
I17: =IF(F17="","",F17*H17)
I18: =IF(F18="","",F18*H18)
I19: =IF(F19="","",F19*H19)
I20: =IF(F20="","",F20*H20)
I21: =IF(F21="","",F21*H21)
I22: =IF(F22="","",F22*H22)
I23: =IF(F23="","",F23*H23)
I24: =IF(F24="","",F24*H24)
I25: =IF(F25="","",F25*H25)
... I53: =IF(F53="","",F53*H53)
A54: TOTAL DEL PERÍODO | I54: =SUM(I4:I53)

Sheet Resumen por Categoría
A1: RESUMEN DE GASTOS POR CATEGORÍA
A2: Se actualiza automáticamente desde la hoja 'Registro de Gastos'
A3: Categoría | B3: Total Gastado ($) | C3: % del Total | D3: Nivel
A4: Sanidad animal | B4: =SUMIF('Registro de Gastos'!C4:C53,A4,'Registro de Gastos'!I4:I53) | C4: =IF(B15=0,"",B4/B15) | D4: =IF(C4="","Sin datos",IF(C4>0.2,"Alto (>20%)",IF(C4>0.1,"Medio (10-20%)","Bajo (<10%)")))
A5: Alimentación animal | B5: =SUMIF('Registro de Gastos'!C4:C53,A5,'Registro de Gastos'!I4:I53) | C5: =IF(B16=0,"",B5/B16) | D5: =IF(C5="","Sin datos",IF(C5>0.2,"Alto (>20%)",IF(C5>0.1,"Medio (10-20%)","Bajo (<10%)")))
A6: Insumos agrícolas | B6: =SUMIF('Registro de Gastos'!C4:C53,A6,'Registro de Gastos'!I4:I53) | C6: =IF(B17=0,"",B6/B17) | D6: =IF(C6="","Sin datos",IF(C6>0.2,"Alto (>20%)",IF(C6>0.1,"Medio (10-20%)","Bajo (<10%)")))
A7: Mano de obra | B7: =SUMIF('Registro de Gastos'!C4:C53,A7,'Registro de Gastos'!I4:I53) | C7: =IF(B18=0,"",B7/B18) | D7: =IF(C7="","Sin datos",IF(C7>0.2,"Alto (>20%)",IF(C7>0.1,"Medio (10-20%)","Bajo (<10%)")))
A8: Maquinaria y equipos | B8: =SUMIF('Registro de Gastos'!C4:C53,A8,'Registro de Gastos'!I4:I53) | C8: =IF(B19=0,"",B8/B19) | D8: =IF(C8="","Sin datos",IF(C8>0.2,"Alto (>20%)",IF(C8>0.1,"Medio (10-20%)","Bajo (<10%)")))
A9: Transporte | B9: =SUMIF('Registro de Gastos'!C4:C53,A9,'Registro de Gastos'!I4:I53) | C9: =IF(B20=0,"",B9/B20) | D9: =IF(C9="","Sin datos",IF(C9>0.2,"Alto (>20%)",IF(C9>0.1,"Medio (10-20%)","Bajo (<10%)")))
A10: Semillas y material vegetal | B10: =SUMIF('Registro de Gastos'!C4:C53,A10,'Registro de Gastos'!I4:I53) | C10: =IF(B21=0,"",B10/B21) | D10: =IF(C10="","Sin datos",IF(C10>0.2,"Alto (>20%)",IF(C10>0.1,"Medio (10-20%)","Bajo (<10%)")))
A11: Administración y otros | B11: =SUMIF('Registro de Gastos'!C4:C53,A11,'Registro de Gastos'!I4:I53) | C11: =IF(B22=0,"",B11/B22) | D11: =IF(C11="","Sin datos",IF(C11>0.2,"Alto (>20%)",IF(C11>0.1,"Medio (10-20%)","Bajo (<10%)")))
A12: TOTAL GENERAL | B12: =SUM(B4:B11)

Sheet Plantillas de Prompt
A1: PLANTILLAS DE PROMPT PARA CLAUDE — CONTROL DE GASTOS
A3: Registro diario | B3: Actúa como contador agropecuario. Voy a darte una lista desordenada de gastos de mi finca de hoy. Categorízalos en: Sanidad animal, Alimentación animal, Insumos agrícolas, Mano de obra, Maquinaria y equipos, Transporte, Semillas y material vegetal, Administración y otros. Para cada categoría muéstrame el subtotal. Al final dame el total del día y dime cuál categoría fue la más alta. Aquí van los gastos: [PEGA AQUÍ TUS GASTOS]
A4: Análisis mensual | B4: Aquí están mis gastos del mes de [MES]: [PEGA DATOS O TOTALES POR CATEGORÍA]. Analízalos y dime: 1) En qué categoría gasté más, 2) Si hay algo que parece inusualmente alto, 3) Qué porcentaje representa cada categoría del total, 4) Una recomendación para reducir costos el próximo mes.
A5: Comparar meses | B5: Compara mis gastos de estos dos meses: Mes 1 [MES]: [TOTALES]. Mes 2 [MES]: [TOTALES]. Dime qué categorías subieron, cuáles bajaron, y el % de variación total. Dame una hipótesis de por qué pudo haber cambiado cada categoría significativa.
A6: Presupuesto vs real | B6: Mi presupuesto mensual para la finca es: [CATEGORÍA: VALOR]. Mis gastos reales fueron: [CATEGORÍA: VALOR]. Dime en qué categorías me pasé del presupuesto, cuánto fue la desviación en pesos y en porcentaje, y qué acciones concretas puedo tomar para ajustarme el próximo mes.
A7: Preparar subasta | B7: Voy a vender [CANTIDAD] [TIPO DE ANIMAL] en la subasta de [LUGAR] el [FECHA]. Mis costos de producción por animal han sido: [DETALLAR O PEGAR GASTOS]. ¿Cuál es el precio mínimo al que debo vender para no perder? ¿Y cuál debería ser mi precio objetivo con un margen del 20%?
